{
  "@context": [
    "http://schema.org/",
    {
      "mentionedBy": {
        "@reverse": "http://schema.org/mentions"
      },
      "performedIn": {
        "@reverse": "http://schema.org/performer"
      },
      "attended": {
        "@reverse": "http://schema.org/attendee"
      },
      "created": {
        "@reverse": "http://schema.org/creator"
      }
    }
  ],
  "id": "https://wragge.github.io/lodbook-james-minahan/organisations/deane-and-deane-solicitors/",
  "location": {
    "id": "https://wragge.github.io/lodbook-james-minahan/places/sydney/",
    "name": "Sydney",
    "type": "City"
  },
  "mainEntityofPage": "https://wragge.github.io/lodbook-james-minahan/organisations/deane-and-deane-solicitors/index.html",
  "mentionedBy": {
    "id": "https://wragge.github.io/lodbook-james-minahan/chapters/chapter-1/",
    "name": "An unexpected welcome",
    "type": "WebPage"
  },
  "name": "Deane and Deane Solicitors",
  "type": "Organization"
}